README.txt
setup.py
hashdb/__init__.py
hashdb/hashdb.py
hashdb/hashdb_config.py
hashdb/hashdb_config_base.py
hashdb/hashdb_config_cmdline.py
hashdb/hashdb_config_file.py
hashdb/hashdb_config_updatedb.py
hashdb/hashdb_db.py
hashdb/hashdb_hash.py
hashdb/hashdb_mntent.py
hashdb/hashdb_mntent_wrapper.py
hashdb/hashdb_onsigint.py
hashdb/hashdb_output.py
hashdb/hashdb_progress.py
hashdb/hashdb_walk.py
hashdb.egg-info/PKG-INFO
hashdb.egg-info/SOURCES.txt
hashdb.egg-info/dependency_links.txt
hashdb.egg-info/entry_points.txt
hashdb.egg-info/requires.txt
hashdb.egg-info/top_level.txt
hashdb.egg-info/zip-safe