Metadata-Version: 1.0
Name: hashdb
Version: 0.2.beta
Summary: Library and Application for building database/s of file hash values
Home-page: http://code.google.com/p/hashdb/
Author: Shamless McShanigans
Author-email: Shamless.McShanigans+hashdb@gmail.com
License: GPL3
Keywords: hash md5 hashdb utility util tool console
Platform: UNKNOWN
Classifier: License :: OSI Approved :: GNU General Public License (GPL)
Classifier: Programming Language :: Python
Classifier: Programming Language :: Python :: 2.6
Classifier: Operating System :: OS Independent
Classifier: Development Status :: 4 - Beta
Classifier: Intended Audience :: Developers
Classifier: Intended Audience :: System Administrators
Classifier: Environment :: Console
Classifier: Natural Language :: English
Classifier: Topic :: Software Development :: Libraries :: Python Modules
Classifier: Topic :: System
Classifier: Topic :: System :: Archiving
Classifier: Topic :: System :: Systems Administration
Classifier: Topic :: Utilities
